[
    {
    "id":1,
    "image":"bojack_deck.jpg"
},
{
    "id":2,
    "image":"bojack-underwater.jpg"
},
{
    "id":3,
    "image":"bojackandPC.jpg"
},
{
    "id":4,
    "image":"bojackdazed.jpg"
},
{
    "id":5,
    "image":"diane.jpg"
},
{
    "id":6,
    "image":"jessicabeil.jpg"
},
{
    "id":7,
    "image":"MrPB.jpg"
},
{
    "id":8,
    "image":"princessCaroline.jpg"
},
{
    "id":9,
    "image":"greyblazer1.jpg"
},
{
    "id":10,
    "image":"greyblazer2.jpg"
},
{
    "id":11,
    "image":"sextina.jpg"
},
{
    "id":12,
    "image":"sadbojack.jpg"
}
]